Metadata-Version: 2.1
Name: adcom
Version: 1.3
Summary: The additional commands to Python!
Home-page: https://github.com/KvaksMan/adcom
Author: KvaksManYT
Author-email: kvaksman225@gmail.com
License: Apache 2.0
Platform: UNKNOWN
